autono/__init__.py
autono/ability/__init__.py
autono/ability/ability.py
autono/ability/agentic_ability.py
autono/ability/base_ability.py
autono/ability/mcp_ability.py
autono/ability/mcp_agentic_ability.py
autono/brain/__init__.py
autono/brain/agent.py
autono/brain/base_agent.py
autono/brain/mcp_agent.py
autono/brain/memory_augment.py
autono/brain/hook/__init__.py
autono/brain/hook/after_action_taken.py
autono/brain/hook/base_hook.py
autono/brain/hook/before_action_taken.py
autono/brain/lm/__init__.py
autono/brain/lm/dashscope.py
autono/brain/lm/deepseek.py
autono/brain/lm/openai.py
autono/enum/Personality.py
autono/enum/__init__.py
autono/exception/__init__.py
autono/exception/invalid_mcp_tool_exception.py
autono/exception/not_a_regular_function_exception.py
autono/exception/null_request_exception.py
autono/exception/too_dumb_exception.py
autono/message/__init__.py
autono/message/after_action_taken_message.py
autono/message/all_done_message.py
autono/message/base_massage.py
autono/message/before_action_taken_message.py
autono/prompt/__init__.py
autono/prompt/analyser_prompt.py
autono/prompt/docstring_prompt.py
autono/prompt/executor_prompt.py
autono/prompt/introspection_prompt.py
autono/prompt/next_move_prompt.py
autono/prompt/prompt.py
autono/prompt/request_resolver_prompt.py
autono/prompt/scheduler_prompt.py
autono/prompt/self_introduce.py
autono/util/__init__.py
autono/util/ability.py
autono/util/agentic.py
autono/util/mcp_session.py
autono/util/synchronized_call.py
autono-1.1.1.dist-info/licenses/LICENSE
autono-1.1.1.dist-info/METADATA
autono-1.1.1.dist-info/WHEEL
autono-1.1.1.dist-info/top_level.txt
autono-1.1.1.dist-info/RECORD
