Metadata-Version: 2.4
Name: autono
Version: 1.1.1
Summary: A ReAct-Based Highly Robust Autonomous Agent Framework
Home-page: https://github.com/vortezwohl/Autono
Author: vortezwohl
Author-email: vortez.wohl@gmail.com
License:                     GNU GENERAL PUBLIC LICENSE
Project-URL: Bug Tracker, https://github.com/vortezwohl/Autono/issues
Classifier: Programming Language :: Python :: 3
Classifier: Operating System :: OS Independent
Classifier: Natural Language :: English
Requires-Python: >=3.10
License-File: LICENSE
Requires-Dist: vortezwohl>=0.0.8
Requires-Dist: json-repair>=0.50.0
Requires-Dist: langchain>=0.3.14
Requires-Dist: langchain-core>=0.3.29
Requires-Dist: langchain-community>=0.3.14
Requires-Dist: langchain-openai>=0.2.3
Requires-Dist: openai>=1.59.3
Requires-Dist: dashscope>=1.20.14
Requires-Dist: websockets>=15.0.1
Requires-Dist: mcp>=1.6.0
Dynamic: author
Dynamic: author-email
Dynamic: classifier
Dynamic: description
Dynamic: description-content-type
Dynamic: home-page
Dynamic: license
Dynamic: license-file
Dynamic: project-url
Dynamic: requires-dist
Dynamic: requires-python
Dynamic: summary
